signalvine_sdk/__init__.py
signalvine_sdk/common.py
signalvine_sdk/sdk.py
signalvine_sdk-0.4.6.dist-info/LICENSE
signalvine_sdk-0.4.6.dist-info/METADATA
signalvine_sdk-0.4.6.dist-info/WHEEL
signalvine_sdk-0.4.6.dist-info/top_level.txt
signalvine_sdk-0.4.6.dist-info/RECORD
