Metadata-Version: 2.1
Name: signalvine-sdk
Version: 0.4.6
Summary: SignalVine API SDK
Home-page: https://github.com/CUBoulder-OIT/signalvine-sdk
Author: CU Boulder, OIT
Author-email: stta9820@colorado.edu
License: Apache License 2.0
Platform: UNKNOWN
Classifier: Programming Language :: Python :: 3
Classifier: License :: OSI Approved :: Apache Software License
Classifier: Operating System :: OS Independent
Requires-Python: >=3.6
Requires-Dist: pandas
Requires-Dist: python-box
